{"stats":{"minecraft:dropped":{"vein_vantage:debris_extractor":1},"minecraft:mined":{"minecraft:emerald_ore":1,"minecraft:coal_ore":2,"minecraft:copper_ore":5,"minecraft:stone":123,"minecraft:andesite":1},"minecraft:picked_up":{"minecraft:raw_copper":112,"minecraft:raw_iron":10,"vein_vantage:debris_extractor":3,"minecraft:andesite":275,"minecraft:cobbled_deepslate":270,"minecraft:gravel":114,"minecraft:granite":561,"minecraft:flint":8,"minecraft:diorite":212,"minecraft:coal":74,"minecraft:dirt":79,"minecraft:cobblestone":7036},"minecraft:used":{"vein_vantage:forge_minerale":3,"minecraft:cobblestone":54,"minecraft:anvil":6,"minecraft:hopper":1,"minecraft:crafting_table":1,"minecraft:andesite":2,"minecraft:netherite_pickaxe":630,"minecraft:stone":5,"vein_vantage:debris_extractor":8},"minecraft:crafted":{"vein_vantage:forge_minerale":1},"minecraft:custom":{"minecraft:time_since_rest":82641,"minecraft:crouch_one_cm":8301,"minecraft:play_time":82641,"minecraft:sprint_one_cm":96012,"minecraft:damage_taken":30,"minecraft:walk_one_cm":134702,"minecraft:sneak_time":3256,"minecraft:walk_under_water_one_cm":10,"minecraft:interact_with_anvil":11,"minecraft:drop":1,"minecraft:jump":126,"minecraft:inspect_hopper":2,"minecraft:leave_game":76,"minecraft:time_since_death":82641,"minecraft:walk_on_water_one_cm":9439,"minecraft:total_world_time":92827,"minecraft:swim_one_cm":1006,"minecraft:interact_with_crafting_table":2,"minecraft:fall_one_cm":1626,"minecraft:fly_one_cm":20194}},"DataVersion":3955}